pylibup/__init__.py
pylibup/classes.py
pylibup/client.py
pylibup/config.py
pylibup/envs.py
pylibup/serializers.py
pylibup/static.py
pylibup/types.py
pylibup/utils.py
pylibup/cli/__init__.py
pylibup/cli/app.py
pylibup/cli/base.py
pylibup-0.0.3.dist-info/LICENSE
pylibup-0.0.3.dist-info/METADATA
pylibup-0.0.3.dist-info/WHEEL
pylibup-0.0.3.dist-info/entry_points.txt
pylibup-0.0.3.dist-info/top_level.txt
pylibup-0.0.3.dist-info/RECORD
