Metadata-Version: 2.1
Name: pylibup
Version: 0.0.3
Summary: Python library Builder with CLI
Home-page: https://github.com/pylibup
Author: Tri Songz
Author-email: ts@growthengineai.com
License: MIT Style
Platform: UNKNOWN
Classifier: Intended Audience :: Developers
Classifier: License :: OSI Approved :: MIT License
Classifier: Programming Language :: Python :: 3.7
Classifier: Topic :: Software Development :: Libraries
License-File: LICENSE
Requires-Dist: typer
Requires-Dist: PyGithub
Requires-Dist: GitPython
Requires-Dist: Jinja2
Requires-Dist: pyyaml
Requires-Dist: pylogz
Requires-Dist: requests
